{"title":"about","uid":"03933793d01427bd4ef056d0a9b02560","text":"关于关于作者很高兴你能看见我。 简单介绍下， 本人一名普通Java后端程序员（会一点前端）， 现就职于重庆某科技公司。 关于博客2020年才毕业的时候，记得当时记忆力超强，学过的技术栈和踩过的坑几乎过目不忘。随着时间打磨，记性似乎不如以前（但也没那么严重），于是想着把工作、学习中...","date":"2023-06-21T16:48:56.000Z","updated":"2023-06-21T17:34:09.360Z","comments":true,"path":"api/pages/about/index.json","covers":null,"excerpt":"","content":"<h1 id=\"关于\"><a href=\"#关于\" class=\"headerlink\" title=\"关于\"></a>关于</h1><h2 id=\"关于作者\"><a href=\"#关于作者\" class=\"headerlink\" title=\"关于作者\"></a>关于作者</h2><p>很高兴你能看见我。</p>\n<p>简单介绍下， 本人一名普通Java后端程序员（会一点前端）， 现就职于重庆某科技公司。 </p>\n<h2 id=\"关于博客\"><a href=\"#关于博客\" class=\"headerlink\" title=\"关于博客\"></a>关于博客</h2><p>2020年才毕业的时候，记得当时记忆力超强，学过的技术栈和踩过的坑几乎过目不忘。随着时间打磨，<br>记性似乎不如以前（但也没那么严重），于是想着把工作、学习中遇到的一些技术问题和坑记录一下。<br>于是就想着起一个博客。</p>\n<p>如果我的分享有不对，欢迎互相讨论；如果能够帮助到你，我会觉得很开心。</p>\n<p>– Life Oriented Programming</p>\n","count_time":{"symbolsCount":232,"symbolsTime":"1 mins."},"toc":"<ol class=\"toc\"><li class=\"toc-item toc-level-1\"><a class=\"toc-link\" href=\"#%E5%85%B3%E4%BA%8E\"><span class=\"toc-text\">关于</span></a><ol class=\"toc-child\"><li class=\"toc-item toc-level-2\"><a class=\"toc-link\" href=\"#%E5%85%B3%E4%BA%8E%E4%BD%9C%E8%80%85\"><span class=\"toc-text\">关于作者</span></a></li><li class=\"toc-item toc-level-2\"><a class=\"toc-link\" href=\"#%E5%85%B3%E4%BA%8E%E5%8D%9A%E5%AE%A2\"><span class=\"toc-text\">关于博客</span></a></li></ol></li></ol>"}